gblog_whisperer/__init__.py
gblog_whisperer/authenticate.py
gblog_whisperer/delete_post.py
gblog_whisperer/post_instantly.py
gblog_whisperer/schedule_post.py
gblog_whisperer-1.0.4.dist-info/METADATA
gblog_whisperer-1.0.4.dist-info/WHEEL
gblog_whisperer-1.0.4.dist-info/top_level.txt
gblog_whisperer-1.0.4.dist-info/RECORD
