Metadata-Version: 2.1
Name: gblog_whisperer
Version: 1.0.4
Summary: GblogWhisperer is the GOAT tool to automate your Blogger posts—whether you’re posting instantly, scheduling, or deleting with no stress.
Classifier: Programming Language :: Python :: 3
Classifier: License :: OSI Approved :: MIT License
Classifier: Operating System :: OS Independent
Requires-Python: >=3.6
Requires-Dist: google-auth-oauthlib>=1.2.1
Requires-Dist: google-api-python-client>=2.154.0
